german_ocr/__init__.py
german_ocr/cli.py
german_ocr/cloud_client.py
german_ocr/extractor.py
german_ocr/hf_backend.py
german_ocr/llamacpp_backend.py
german_ocr/ocr.py
german_ocr/ollama_backend.py
german_ocr/utils.py
german_ocr-0.6.0.dist-info/licenses/LICENSE
german_ocr-0.6.0.dist-info/METADATA
german_ocr-0.6.0.dist-info/WHEEL
german_ocr-0.6.0.dist-info/entry_points.txt
german_ocr-0.6.0.dist-info/top_level.txt
german_ocr-0.6.0.dist-info/RECORD
