Metadata-Version: 2.4
Name: german-ocr
Version: 0.6.0
Summary: High-performance German document OCR - Local & Cloud with GPU/CPU support
Author-email: Keyvan Hardani <hello@keyvan.ai>
Maintainer-email: Keyvan Hardani <hello@keyvan.ai>
License: Apache-2.0
Project-URL: Homepage, https://github.com/Keyvanhardani/german-ocr
Project-URL: Documentation, https://github.com/Keyvanhardani/german-ocr#readme
Project-URL: Repository, https://github.com/Keyvanhardani/german-ocr
Project-URL: Issues, https://github.com/Keyvanhardani/german-ocr/issues
Project-URL: Changelog, https://github.com/Keyvanhardani/german-ocr/releases
Keywords: ocr,german,document,invoice,text-extraction,dsgvo,llama-cpp,gguf,vision-language-model,local-ai,cpu-inference,gpu-inference,document-ai
Classifier: Development Status :: 4 - Beta
Classifier: Intended Audience :: Developers
Classifier: Intended Audience :: Science/Research
Classifier: License :: OSI Approved :: Apache Software License
Classifier: Operating System :: OS Independent
Classifier: Programming Language :: Python :: 3
Classifier: Programming Language :: Python :: 3.9
Classifier: Programming Language :: Python :: 3.10
Classifier: Programming Language :: Python :: 3.11
Classifier: Programming Language :: Python :: 3.12
Classifier: Topic :: Scientific/Engineering :: Artificial Intelligence
Classifier: Topic :: Scientific/Engineering :: Image Recognition
Classifier: Topic :: Text Processing :: Linguistic
Requires-Python: >=3.9
License-File: LICENSE
Requires-Dist: Pillow>=9.0.0
Requires-Dist: httpx>=0.24.0
Requires-Dist: requests>=2.28.0
Provides-Extra: hf
Requires-Dist: torch>=2.0.0; extra == "hf"
Requires-Dist: transformers>=4.40.0; extra == "hf"
Requires-Dist: qwen-vl-utils>=0.0.10; extra == "hf"
Provides-Extra: llamacpp
Requires-Dist: llama-cpp-python>=0.2.0; extra == "llamacpp"
Provides-Extra: cuda
Requires-Dist: torch>=2.0.0; extra == "cuda"
Requires-Dist: llama-cpp-python>=0.2.0; extra == "cuda"
Provides-Extra: all
Requires-Dist: german-ocr[hf,llamacpp]; extra == "all"
Provides-Extra: dev
Requires-Dist: pytest>=7.0.0; extra == "dev"
Requires-Dist: pytest-cov>=4.0.0; extra == "dev"
Requires-Dist: black>=23.0.0; extra == "dev"
Requires-Dist: isort>=5.12.0; extra == "dev"
Requires-Dist: mypy>=1.0.0; extra == "dev"
Dynamic: license-file
